match_variant/__init__.py
match_variant/enum.py
match_variant/maybe.py
match_variant/result.py
match_variant/variant.py
match_variant-2022.10.0a1.dist-info/LICENSE
match_variant-2022.10.0a1.dist-info/WHEEL
match_variant-2022.10.0a1.dist-info/METADATA
match_variant-2022.10.0a1.dist-info/RECORD
