Metadata-Version: 2.1
Name: match-variant
Version: 2022.10.0a1
Summary: Variant algebraic types
Author-email: Brett Cannon <brett@python.org>, Dusty Phillips <dusty@phillips.codes>
Requires-Python: >=3.10
Classifier: License :: OSI Approved :: MIT License
Requires-Dist: pytest ; extra == "test"
Project-URL: Home, https://github.com/dusty-phillips/match-variant
Provides-Extra: test
